referral/__init__.py
referral/admin.py
referral/apps.py
referral/conf.py
referral/faker_factories.py
referral/helpers.py
referral/signals_define.py
referral/api/__init__.py
referral/api/serializers.py
referral/api/urls.py
referral/api/views/__init__.py
referral/api/views/campaign_views.py
referral/api/views/webhooks.py
referral/management/__init__.py
referral/management/commands/__init__.py
referral/management/commands/add_users_to_campaign.py
referral/migrations/0001_initial.py
referral/migrations/0002_remove_campaign_users.py
referral/migrations/0003_auto_20190918_0349.py
referral/migrations/__init__.py
referral/models/__init__.py
referral/models/campaign.py
referral/models/subscriber.py
referral/signals/__init__.py
referral/signals/subscriber.py
referral/tasks/__init__.py
referral/tasks/campaign.py
referral/tasks/subscriber.py
django_earlyparrot-0.2.9.dist-info/AUTHORS.rst
django_earlyparrot-0.2.9.dist-info/LICENSE
django_earlyparrot-0.2.9.dist-info/METADATA
django_earlyparrot-0.2.9.dist-info/WHEEL
django_earlyparrot-0.2.9.dist-info/top_level.txt
django_earlyparrot-0.2.9.dist-info/RECORD
