Metadata-Version: 2.1
Name: django-earlyparrot
Version: 0.2.9
Summary: Use EarlyParrot with Django webhooks and signals
Home-page: https://github.com/exolever/django-earlyparrot
Author: marfyl
Author-email: marfyl.dev@gmail.com
License: MIT
Keywords: python,django,earlyparrot,early,parrot
Platform: UNKNOWN
Classifier: Development Status :: 5 - Production/Stable
Classifier: Environment :: Web Environment
Classifier: Framework :: Django :: 1.11
Classifier: Framework :: Django :: 2.0
Classifier: Intended Audience :: Developers
Classifier: License :: OSI Approved :: BSD License
Classifier: Natural Language :: English
Classifier: Operating System :: OS Independent
Classifier: Programming Language :: Python :: Implementation :: PyPy
Classifier: Programming Language :: Python
Classifier: Programming Language :: Python :: 3.6
License-File: LICENSE
License-File: AUTHORS.rst
Requires-Dist: django-appconf
Requires-Dist: django-model-utils
Requires-Dist: djangorestframework
Requires-Dist: celery
Requires-Dist: psycopg2-binary
Requires-Dist: redis
Requires-Dist: requests
